pyros_cli/__init__.py
pyros_cli/globals.py
pyros_cli/main.py
pyros_cli/agents/enhance_agent.py
pyros_cli/agents/flock_handler.py
pyros_cli/agents/orchestrator_agent.py
pyros_cli/agents/tools.py
pyros_cli/library/prompt_vars/75k.md
pyros_cli/library/prompt_vars/animal.md
pyros_cli/library/prompt_vars/builder/Style_shot.txt
pyros_cli/library/prompt_vars/builder/background_abstract.txt
pyros_cli/library/prompt_vars/builder/background_bathtub.txt
pyros_cli/library/prompt_vars/builder/background_beautiful.txt
pyros_cli/library/prompt_vars/builder/background_beds.txt
pyros_cli/library/prompt_vars/builder/background_buildings.txt
pyros_cli/library/prompt_vars/builder/background_caves.txt
pyros_cli/library/prompt_vars/builder/background_crowded_place.txt
pyros_cli/library/prompt_vars/builder/background_fantasy_themed.txt
pyros_cli/library/prompt_vars/builder/background_futuristic.txt
pyros_cli/library/prompt_vars/builder/background_horror_place.txt
pyros_cli/library/prompt_vars/builder/background_interiors.txt
pyros_cli/library/prompt_vars/builder/background_interiors_fantasy.txt
pyros_cli/library/prompt_vars/builder/background_other.txt
pyros_cli/library/prompt_vars/builder/background_spaceships.txt
pyros_cli/library/prompt_vars/builder/background_spooky.txt
pyros_cli/library/prompt_vars/builder/background_weather.txt
pyros_cli/library/prompt_vars/builder/body_anthro.txt
pyros_cli/library/prompt_vars/builder/body_breast_size.txt
pyros_cli/library/prompt_vars/builder/body_nipples.txt
pyros_cli/library/prompt_vars/builder/body_penis.txt
pyros_cli/library/prompt_vars/builder/body_pubes.txt
pyros_cli/library/prompt_vars/builder/body_skin_color_fanatsy.txt
pyros_cli/library/prompt_vars/builder/body_tattoos.txt
pyros_cli/library/prompt_vars/builder/body_vaginas.txt
pyros_cli/library/prompt_vars/builder/body_wings.txt
pyros_cli/library/prompt_vars/builder/clothing_accessories.txt
pyros_cli/library/prompt_vars/builder/clothing_asian.txt
pyros_cli-0.1.1.dist-info/METADATA
pyros_cli-0.1.1.dist-info/WHEEL
pyros_cli-0.1.1.dist-info/entry_points.txt
pyros_cli-0.1.1.dist-info/RECORD
